{
  "contest": {
    "id": "agc017",
    "title": "AtCoder Grand Contest 017",
    "url": "https://atcoder.jp/contests/agc017"
  },
  "tasks": [
    {
      "id": "agc017_a",
      "label": "A",
      "title": "Biscuits",
      "url": "https://atcoder.jp/contests/agc017/tasks/agc017_a",
      "directory": {
        "path": "a",
        "testdir": "test",
        "submit": "agc017_a.cpp"
      }
    },
    {
      "id": "agc017_b",
      "label": "B",
      "title": "Moderate Differences",
      "url": "https://atcoder.jp/contests/agc017/tasks/agc017_b",
      "directory": {
        "path": "b",
        "testdir": "test",
        "submit": "agc017_b.cpp"
      }
    },
    {
      "id": "agc017_c",
      "label": "C",
      "title": "Snuke and Spells",
      "url": "https://atcoder.jp/contests/agc017/tasks/agc017_c",
      "directory": {
        "path": "c",
        "testdir": "test",
        "submit": "agc017_c.cpp"
      }
    },
    {
      "id": "agc017_d",
      "label": "D",
      "title": "Game on Tree",
      "url": "https://atcoder.jp/contests/agc017/tasks/agc017_d",
      "directory": {
        "path": "d",
        "testdir": "test",
        "submit": "agc017_d.cpp"
      }
    },
    {
      "id": "agc017_e",
      "label": "E",
      "title": "Jigsaw",
      "url": "https://atcoder.jp/contests/agc017/tasks/agc017_e",
      "directory": {
        "path": "e",
        "testdir": "test",
        "submit": "agc017_e.cpp"
      }
    },
    {
      "id": "agc017_f",
      "label": "F",
      "title": "Zigzag",
      "url": "https://atcoder.jp/contests/agc017/tasks/agc017_f",
      "directory": {
        "path": "f",
        "testdir": "test",
        "submit": "agc017_f.cpp"
      }
    }
  ]
}